{
  "_class": "shapeGroup",
  "booleanOperation": 0,
  "clippingMaskMode": 0,
  "do_objectID": "483E21C3-277E-4CF4-B14B-18124B8A8F6A",
  "exportOptions": {
    "_class": "exportOptions",
    "do_objectID": "F8CCF7F5-C73C-47B1-B33C-348984C46494",
    "exportFormats": [
    ],
    "includedLayerIds": [
    ],
    "layerOptions": 0,
    "shouldTrim": false
  },
  "frame": {
    "_class": "rect",
    "constrainProportions": false,
    "do_objectID": "2F7B4FF6-2B36-4A79-B08F-DAFC040F2B3D",
    "height": 14,
    "width": 4,
    "x": 352,
    "y": 34
  },
  "hasClickThrough": false,
  "hasClippingMask": false,
  "isFixedToViewport": false,
  "isFlippedHorizontal": false,
  "isFlippedVertical": false,
  "isLocked": false,
  "isVisible": true,
  "layerListExpandedType": 1,
  "layers": [
    {
      "class": "shapePath",
      "id": "03854E1F-4BF0-4021-8A40-89EAE84BCFCA"
    },
    {
      "class": "shapePath",
      "id": "7BC14B5C-818D-4516-B7AC-912430FE0548"
    },
    {
      "class": "shapePath",
      "id": "7E37B485-F20F-440A-9135-7DA07530BA2F"
    }
  ],
  "name": "Icon/Dots",
  "nameIsFixed": true,
  "resizingConstraint": 63,
  "resizingType": 0,
  "rotation": 0,
  "shouldBreakMaskChain": false,
  "style": {
    "_class": "style",
    "do_objectID": "DBE279F8-646D-41EA-8726-D6BDA19BBED2",
    "endMarkerType": 0,
    "fills": [
      {
        "_class": "fill",
        "color": {
          "_class": "color",
          "alpha": 0.56,
          "blue": 0,
          "green": 0,
          "red": 0
        },
        "fillType": 0,
        "isEnabled": true,
        "noiseIndex": 0,
        "noiseIntensity": 0,
        "patternFillType": 1,
        "patternTileScale": 1
      }
    ],
    "miterLimit": 10,
    "startMarkerType": 0,
    "windingRule": 0
  },
  "userInfo": {
    "com.animaapp.stc-sketch-plugin": {
      "kModelPropertiesKey": {
      }
    }
  },
  "windingRule": 0
}