{
  "_class": "group",
  "booleanOperation": 0,
  "clippingMaskMode": 0,
  "do_objectID": "B1DCA7D9-7ABC-4E71-BBE1-6D3CF6A5C56E",
  "exportOptions": {
    "_class": "exportOptions",
    "do_objectID": "48D524A3-69DE-4A67-ACCB-A7A42638C28C",
    "exportFormats": [
    ],
    "includedLayerIds": [
    ],
    "layerOptions": 0,
    "shouldTrim": false
  },
  "frame": {
    "_class": "rect",
    "constrainProportions": false,
    "do_objectID": "A706DCD8-70DE-4D65-A13A-95CFEFB2F541",
    "height": 34,
    "width": 34,
    "x": 0,
    "y": 0
  },
  "hasClickThrough": false,
  "hasClippingMask": false,
  "isFixedToViewport": false,
  "isFlippedHorizontal": false,
  "isFlippedVertical": false,
  "isLocked": false,
  "isVisible": true,
  "layerListExpandedType": 0,
  "layers": [
    {
      "class": "shapePath",
      "id": "C583865A-E87E-4325-918E-9C03577E059D"
    },
    {
      "class": "shapePath",
      "id": "0B9299E2-0D1A-4743-8ED5-2A2987744FB2"
    }
  ],
  "name": "Group 5",
  "nameIsFixed": false,
  "resizingConstraint": 63,
  "resizingType": 0,
  "rotation": 0,
  "shouldBreakMaskChain": false,
  "style": {
    "_class": "style",
    "do_objectID": "4BB289DA-BBAB-4499-8F04-8ABA1FFF6989",
    "endMarkerType": 0,
    "miterLimit": 10,
    "startMarkerType": 0,
    "windingRule": 1
  },
  "userInfo": {
    "com.animaapp.stc-sketch-plugin": {
      "kModelPropertiesKey": {
      }
    }
  }
}