{
  "_class": "symbolInstance",
  "booleanOperation": -1,
  "clippingMaskMode": 0,
  "do_objectID": "7CFA6731-29F6-4DBE-B5D3-B267DD0448B2",
  "exportOptions": {
    "_class": "exportOptions",
    "exportFormats": [
    ],
    "includedLayerIds": [
    ],
    "layerOptions": 0,
    "shouldTrim": false
  },
  "frame": {
    "_class": "rect",
    "constrainProportions": false,
    "height": 60,
    "width": 1140,
    "x": 140,
    "y": 617
  },
  "hasClippingMask": false,
  "horizontalSpacing": 0,
  "isFixedToViewport": false,
  "isFlippedHorizontal": false,
  "isFlippedVertical": false,
  "isLocked": false,
  "isVisible": true,
  "layerListExpandedType": 0,
  "name": "Team List Row Copy 3",
  "nameIsFixed": false,
  "overrideValues": [
    {
      "_class": "overrideValue",
      "do_objectID": "59DA9C12-395A-4485-B262-3FAE1EF151FC",
      "overrideName": "B2446C56-7AE7-4ABB-ABF6-3F8BB88624C8_stringValue",
      "value": "jast.amely@gmail.com"
    },
    {
      "_class": "overrideValue",
      "do_objectID": "D10A87CB-AAE4-4643-A1A7-8C4C6FEB5DDD",
      "overrideName": "6AAC9572-EC46-4E0B-8759-FCDC40E339D4_stringValue",
      "value": "Francisco Walker"
    }
  ],
  "resizingConstraint": 63,
  "resizingType": 0,
  "rotation": 0,
  "scale": 1,
  "shouldBreakMaskChain": false,
  "style": {
    "_class": "style",
    "endMarkerType": 0,
    "miterLimit": 10,
    "startMarkerType": 0,
    "windingRule": 1
  },
  "symbolID": "39EB14E5-FEB5-4C49-81E7-56AC26FA64B3",
  "userInfo": {
    "com.animaapp.stc-sketch-plugin": {
      "kModelPropertiesKey": {
      }
    }
  },
  "verticalSpacing": 0
}